csiMVP/Common/__init__.py
csiMVP/Common/init.py
csiMVP/Common/remote_open.py
csiMVP/Common/sequence.py
csiMVP/Common/tf_config_load.py
csiMVP/Dependencies/elastic_search_init.py
csiMVP/Toolbox/__init__.py
csiMVP/Toolbox/aws_init.py
csiMVP/Toolbox/consolidate.py
csiMVP/Toolbox/filenames.py
csiMVP/Toolbox/goodies.py
csiMVP/Toolbox/json_encoder.py
csiMVP/Toolbox/obo.py
csiMVP/Toolbox/retry.py
csiMVP/Toolbox/sqs_init.py
csiMVP/Toolbox/supabase.py
csi_genai_lib/__init__.py
csi_genai_lib/__main__.py
csi_genai_lib/main.py
csi_genai_lib/post_sqs.py
csi_genai_lib/streamtap.py
csi_genai_lib-0.1.34.dist-info/METADATA
csi_genai_lib-0.1.34.dist-info/WHEEL
csi_genai_lib-0.1.34.dist-info/top_level.txt
csi_genai_lib-0.1.34.dist-info/RECORD
